clickhouse_mysql/__init__.py
clickhouse_mysql/clioptions.py
clickhouse_mysql/config.py
clickhouse_mysql/daemon.py
clickhouse_mysql/main.py
clickhouse_mysql/objectbuilder.py
clickhouse_mysql/observable.py
clickhouse_mysql/pumper.py
clickhouse_mysql/tablemigrator.py
clickhouse_mysql/tableprocessor.py
clickhouse_mysql/tablesqlbuilder.py
clickhouse_mysql/util.py
clickhouse_mysql/converter/__init__.py
clickhouse_mysql/converter/chwriteconverter.py
clickhouse_mysql/converter/converter.py
clickhouse_mysql/converter/csvreadconverter.py
clickhouse_mysql/converter/csvwriteconverter.py
clickhouse_mysql/dbclient/__init__.py
clickhouse_mysql/dbclient/chclient.py
clickhouse_mysql/dbclient/mysqlclient.py
clickhouse_mysql/event/__init__.py
clickhouse_mysql/event/event.py
clickhouse_mysql/pool/__init__.py
clickhouse_mysql/pool/bbpool.py
clickhouse_mysql/pool/pool.py
clickhouse_mysql/reader/__init__.py
clickhouse_mysql/reader/csvreader.py
clickhouse_mysql/reader/mysqlreader.py
clickhouse_mysql/reader/reader.py
clickhouse_mysql/writer/__init__.py
clickhouse_mysql/writer/chcsvwriter.py
clickhouse_mysql/writer/chwriter.py
clickhouse_mysql/writer/csvwriter.py
clickhouse_mysql/writer/poolwriter.py
clickhouse_mysql/writer/processwriter.py
clickhouse_mysql/writer/writer.py
clickhouse_mysql-0.0.20200128.dist-info/DESCRIPTION.rst
clickhouse_mysql-0.0.20200128.dist-info/METADATA
clickhouse_mysql-0.0.20200128.dist-info/RECORD
clickhouse_mysql-0.0.20200128.dist-info/WHEEL
clickhouse_mysql-0.0.20200128.dist-info/entry_points.txt
clickhouse_mysql-0.0.20200128.dist-info/metadata.json
clickhouse_mysql-0.0.20200128.dist-info/top_level.txt
clickhouse_mysql.etc/clickhouse-mysql.conf
clickhouse_mysql.init.d/clickhouse-mysql
clickhouse_mysql.init.d/clickhouse-mysql.service
clickhouse_mysql_converter/chwritedataconverter.py
clickhouse_mysql_examples/airline_ontime_data_download.sh
clickhouse_mysql_examples/airline_ontime_data_mysql_to_ch_migration.sh
clickhouse_mysql_examples/airline_ontime_data_mysql_to_ch_reader.sh
clickhouse_mysql_examples/airline_ontime_mysql_data_import.sh
clickhouse_mysql_examples/airline_ontime_schema_ch.sql
clickhouse_mysql_examples/airline_ontime_schema_mysql.sql
clickhouse_mysql_examples/datatypes.sh
