Metadata-Version: 2.0
Name: clickhouse-mysql
Version: 0.0.20200128
Summary: MySQL to ClickHouse data migrator
Home-page: https://github.com/altinity/clickhouse-mysql-data-reader
Author: Vladislav Klimenko
Author-email: sunsingerus@gmail.com
License: MIT
Keywords: clickhouse mysql data migration
Platform: UNKNOWN
Classifier: Development Status :: 3 - Alpha
Classifier: Intended Audience :: Developers
Classifier: Intended Audience :: System Administrators
Classifier: Topic :: Database
Classifier: License :: OSI Approved :: MIT License
Classifier: Programming Language :: Python
Classifier: Programming Language :: Python :: 3
Classifier: Programming Language :: Python :: 3.4
Classifier: Programming Language :: Python :: 3.5
Classifier: Programming Language :: Python :: 3.6
Classifier: Programming Language :: Python :: 3 :: Only
Requires-Dist: mysqlclient
Requires-Dist: mysql-replication
Requires-Dist: clickhouse-driver
Requires-Dist: configobj
Requires-Dist: setuptools
